{
  "code": 0,
  "message": "길찾기를 성공하였습니다.",
  "currentDateTime": "2022-08-15T18:27:39",
  "route": {
    "trafast": [
      {
        "summary": {
          "start": {
            "location": [
              127.1882456,
              37.2306795
            ]
          },
          "goal": {
            "location": [
              127.1888283,
              37.2339919
            ],
            "dir": 2
          },
          "distance": 374,
          "duration": 79517,
          "etaServiceType": 0,
          "departureTime": "2022-08-15T18:27:39",
          "bbox": [
            [
              127.1881369,
              37.2306795
            ],
            [
              127.1888283,
              37.234006
            ]
          ],
          "tollFare": 0,
          "taxiFare": 3800,
          "fuelPrice": 47
        },
        "path": [
          [
            127.188279,
            37.2307653
          ],
          [
            127.1882384,
            37.230776
          ],
          [
            127.1881369,
            37.230791
          ],
          [
            127.1881821,
            37.2310291
          ],
          [
            127.1881998,
            37.2311247
          ],
          [
            127.1882119,
            37.2311914
          ],
          [
            127.188224,
            37.2312663
          ],
          [
            127.1883036,
            37.2316496
          ],
          [
            127.1883355,
            37.2318408
          ],
          [
            127.1883586,
            37.2319797
          ],
          [
            127.1883817,
            37.2321149
          ],
          [
            127.1884059,
            37.2322583
          ],
          [
            127.1884334,
            37.232426
          ],
          [
            127.1884565,
            37.2325721
          ],
          [
            127.1884851,
            37.2327471
          ],
          [
            127.1885047,
            37.2328941
          ],
          [
            127.1885201,
            37.2329915
          ],
          [
            127.1886192,
            37.2335785
          ],
          [
            127.1886269,
            37.2336281
          ],
          [
            127.1886301,
            37.2336516
          ],
          [
            127.1886444,
            37.2337499
          ],
          [
            127.1886851,
            37.234006
          ]
        ],
        "section": [
          {
            "pointIndex": 0,
            "pointCount": 3,
            "distance": 13,
            "name": "명지로55번길",
            "congestion": 3,
            "speed": 7
          },
          {
            "pointIndex": 2,
            "pointCount": 19,
            "distance": 332,
            "name": "명지로",
            "congestion": 3,
            "speed": 18
          }
        ],
        "guide": [
          {
            "pointIndex": 2,
            "type": 3,
            "instructions": "'명지로' 방면으로 우회전",
            "distance": 13,
            "duration": 6685
          },
          {
            "pointIndex": 21,
            "type": 88,
            "instructions": "목적지",
            "distance": 361,
            "duration": 72832
          }
        ]
      }
    ]
  }
}